scanbuddy/__init__.py
scanbuddy/__version__.py
scanbuddy/broker/__init__.py
scanbuddy/broker/redis.py
scanbuddy/common/__init__.py
scanbuddy/config/__init__.py
scanbuddy/proc/__init__.py
scanbuddy/proc/bold.py
scanbuddy/proc/converter.py
scanbuddy/proc/fdata.py
scanbuddy/proc/localizer.py
scanbuddy/proc/params.py
scanbuddy/proc/snr.py
scanbuddy/proc/vnav.py
scanbuddy/proc/volreg.py
scanbuddy/view/__init__.py
scanbuddy/view/dash.py
scanbuddy/watcher/__init__.py
scanbuddy/watcher/dicom.py
scanbuddy/watcher/directory.py
scanbuddy-0.4.2.data/scripts/simulator.py
scanbuddy-0.4.2.data/scripts/start.py
scanbuddy-0.4.2.dist-info/LICENSE
scanbuddy-0.4.2.dist-info/METADATA
scanbuddy-0.4.2.dist-info/WHEEL
scanbuddy-0.4.2.dist-info/top_level.txt
scanbuddy-0.4.2.dist-info/RECORD
