Metadata-Version: 2.1
Name: scanbuddy
Version: 0.4.2
Summary: fMRI Motion Plotting and SNR Calculation
Home-page: https://github.com/harvard-nrg/scanbuddy
Author: Neuroinformatics Research Group
Author-email: info@neuroinfo.org
License-File: LICENSE
Requires-Dist: dash
Requires-Dist: dash-bootstrap-components
Requires-Dist: pydicom
Requires-Dist: PyPubSub
Requires-Dist: watchdog
Requires-Dist: numpy
Requires-Dist: sortedcontainers
Requires-Dist: plotly
Requires-Dist: pandas
Requires-Dist: retry
Requires-Dist: redis
Requires-Dist: pyyaml
Requires-Dist: jsonpath-ng
Requires-Dist: dash_auth
Requires-Dist: nibabel
Requires-Dist: psutil
Requires-Dist: tabulate
